[{"Major_category":"Physical Sciences","Gender":"Men","Count":832,"Percent":0.004485683015328},{"Major_category":"Physical Sciences","Gender":"Men","Count":528,"Percent":0.002846683452035},{"Major_category":"Physical Sciences","Gender":"Men","Count":23080,"Percent":0.124434572107894},{"Major_category":"Physical Sciences","Gender":"Men","Count":752,"Percent":0.004054367340777},{"Major_category":"Physical Sciences","Gender":"Men","Count":894,"Percent":0.004819952663105},{"Major_category":"Physical Sciences","Gender":"Men","Count":32923,"Percent":0.177502574415432},{"Major_category":"Physical Sciences","Gender":"Men","Count":5813,"Percent":0.031340475202044},{"Major_category":"Physical Sciences","Gender":"Men","Count":809,"Percent":0.004361679758895},{"Major_category":"Physical Sciences","Gender":"Men","Count":27015,"Percent":0.145649911849859},{"Major_category":"Physical Sciences","Gender":"Men","Count":2744,"Percent":0.014794127637091},{"Major_category":"Physical Sciences","Gender":"Women","Count":960,"Percent":0.005175788094609},{"Major_category":"Physical Sciences","Gender":"Women","Count":1588,"Percent":0.008561616139833},{"Major_category":"Physical Sciences","Gender":"Women","Count":9062,"Percent":0.048857283034737},{"Major_category":"Physical Sciences","Gender":"Women","Count":1666,"Percent":0.00898214892252},{"Major_category":"Physical Sciences","Gender":"Women","Count":542,"Percent":0.002922163695081},{"Major_category":"Physical Sciences","Gender":"Women","Count":33607,"Percent":0.181190323432841},{"Major_category":"Physical Sciences","Gender":"Women","Count":5159,"Percent":0.027814469562592},{"Major_category":"Physical Sciences","Gender":"Women","Count":1169,"Percent":0.006302600294373},{"Major_category":"Physical Sciences","Gender":"Women","Count":35037,"Percent":0.188900091115436},{"Major_category":"Physical Sciences","Gender":"Women","Count":1299,"Percent":0.007003488265518}]