[{"Major_category":"Agriculture & Natural Resources","Low_Other":"income: low-wage","Count":1362,"Percent":0.021349970216635},{"Major_category":"Agriculture & Natural Resources","Low_Other":"income: low-wage","Count":839,"Percent":0.01315170705709},{"Major_category":"Agriculture & Natural Resources","Low_Other":"income: low-wage","Count":94,"Percent":0.001473492804966},{"Major_category":"Agriculture & Natural Resources","Low_Other":"income: low-wage","Count":1405,"Percent":0.02202401479763},{"Major_category":"Agriculture & Natural Resources","Low_Other":"income: low-wage","Count":327,"Percent":0.005125873906637},{"Major_category":"Agriculture & Natural Resources","Low_Other":"income: low-wage","Count":0,"Percent":0.0},{"Major_category":"Agriculture & Natural Resources","Low_Other":"income: low-wage","Count":1231,"Percent":0.019296485562906},{"Major_category":"Agriculture & Natural Resources","Low_Other":"income: low-wage","Count":2125,"Percent":0.033310342665454},{"Major_category":"Agriculture & Natural Resources","Low_Other":"income: low-wage","Count":31,"Percent":0.000485939116531},{"Major_category":"Agriculture & Natural Resources","Low_Other":"income: other","Count":10961,"Percent":0.171818666332257},{"Major_category":"Agriculture & Natural Resources","Low_Other":"income: other","Count":8045,"Percent":0.126109038467567},{"Major_category":"Agriculture & Natural Resources","Low_Other":"income: other","Count":2080,"Percent":0.032604947173715},{"Major_category":"Agriculture & Natural Resources","Low_Other":"income: other","Count":10392,"Percent":0.162899332225601},{"Major_category":"Agriculture & Natural Resources","Low_Other":"income: other","Count":2680,"Percent":0.042010220396903},{"Major_category":"Agriculture & Natural Resources","Low_Other":"income: other","Count":613,"Percent":0.009609054143023},{"Major_category":"Agriculture & Natural Resources","Low_Other":"income: other","Count":5363,"Percent":0.084067467159921},{"Major_category":"Agriculture & Natural Resources","Low_Other":"income: other","Count":14987,"Percent":0.234928049659843},{"Major_category":"Agriculture & Natural Resources","Low_Other":"income: other","Count":1259,"Percent":0.019735398313321}]